{"cameraMode":{"drawMode":0,"name":"Shaded","section":"Shading Mode"},"sceneLighting":true,"audioPlay":false,"sceneViewState":{"showFog":true,"showMaterialUpdate":false,"showSkybox":false,"showFlares":true,"showImageEffects":true,"showParticleSystems":true,"showVisualEffectGraphs":true,"m_FxEnabled":true},"in2DMode":false,"pivot":{"x":52.94123458862305,"y":3.5660321712493898,"z":-5.476993560791016},"rotation":{"x":-0.1152055412530899,"y":-0.7461560368537903,"z":0.12392427027225495,"w":-0.6448502540588379},"size":2.3450980186462404,"orthographic":false}